abdo_dev_innvb/__init__.py
abdo_dev_innvb-0.0.2.dist-info/licenses/LICENSE
abdo_dev_innvb-0.0.2.dist-info/METADATA
abdo_dev_innvb-0.0.2.dist-info/WHEEL
abdo_dev_innvb-0.0.2.dist-info/top_level.txt
abdo_dev_innvb-0.0.2.dist-info/RECORD
