Metadata-Version: 2.4
Name: abdo_dev_innvb
Version: 0.0.2
Summary: A simple library to run Python files on Linux.
Author-email: Abdo <author@example.com>
Project-URL: Homepage, https://github.com/pypa/sampleproject
Project-URL: Bug Tracker, https://github.com/pypa/sampleproject/issues
Classifier: Programming Language :: Python :: 3
Classifier: License :: OSI Approved :: MIT License
Classifier: Operating System :: POSIX :: Linux
Requires-Python: >=3.7
License-File: LICENSE
Dynamic: license-file
